{
  "description": "Extract supplier invoice fields for Northwind Horizon accounts payable",
  "scenario": "document",
  "fields": {
    "invoice_number":   { "type": "string" },
    "invoice_date":     { "type": "date" },
    "supplier_name":    { "type": "string" },
    "supplier_address": { "type": "string" },
    "total_amount":     { "type": "number" },
    "currency":         { "type": "string" },
    "line_items": {
      "type": "array",
      "items": {
        "type": "object",
        "properties": {
          "description": { "type": "string" },
          "quantity":    { "type": "number" },
          "unit_price":  { "type": "number" },
          "line_total":  { "type": "number" }
        }
      }
    }
  }
}
